CHANGELOG.rst
MANIFEST.in
README.rst
setup.py
ripozo_sqlalchemy/__init__.py
ripozo_sqlalchemy/alchemymanager.py
ripozo_sqlalchemy/easy_resource.py
ripozo_sqlalchemy/session_handlers.py
ripozo_sqlalchemy.egg-info/PKG-INFO
ripozo_sqlalchemy.egg-info/SOURCES.txt
ripozo_sqlalchemy.egg-info/dependency_links.txt
ripozo_sqlalchemy.egg-info/requires.txt
ripozo_sqlalchemy.egg-info/top_level.txt